odoo10_addon_account_cash_invoice-10.0.1.0.0-py2.7-nspkg.pth
odoo/addons/account_cash_invoice/README.rst
odoo/addons/account_cash_invoice/__init__.py
odoo/addons/account_cash_invoice/__manifest__.py
odoo/addons/account_cash_invoice/models/__init__.py
odoo/addons/account_cash_invoice/models/account_bank_statement_line.py
odoo/addons/account_cash_invoice/static/description/icon.png
odoo/addons/account_cash_invoice/tests/__init__.py
odoo/addons/account_cash_invoice/tests/test_pay_invoice.py
odoo/addons/account_cash_invoice/wizard/__init__.py
odoo/addons/account_cash_invoice/wizard/cash_invoice_in.py
odoo/addons/account_cash_invoice/wizard/cash_invoice_in.xml
odoo/addons/account_cash_invoice/wizard/cash_invoice_out.py
odoo/addons/account_cash_invoice/wizard/cash_invoice_out.xml
odoo10_addon_account_cash_invoice-10.0.1.0.0.dist-info/DESCRIPTION.rst
odoo10_addon_account_cash_invoice-10.0.1.0.0.dist-info/METADATA
odoo10_addon_account_cash_invoice-10.0.1.0.0.dist-info/RECORD
odoo10_addon_account_cash_invoice-10.0.1.0.0.dist-info/WHEEL
odoo10_addon_account_cash_invoice-10.0.1.0.0.dist-info/metadata.json
odoo10_addon_account_cash_invoice-10.0.1.0.0.dist-info/namespace_packages.txt
odoo10_addon_account_cash_invoice-10.0.1.0.0.dist-info/top_level.txt
